ics_to_datasette/__init__.py
ics_to_datasette-0.3.0.dist-info/METADATA
ics_to_datasette-0.3.0.dist-info/WHEEL
ics_to_datasette-0.3.0.dist-info/entry_points.txt
ics_to_datasette-0.3.0.dist-info/RECORD
