Metadata-Version: 2.1
Name: ics-to-datasette
Version: 0.3.0
Summary: Convert an ICS file to a SQLite database
Home-page: https://github.com/iloveitaly/ics-to-datasette
License: MIT
Keywords: ics,calendar,datasette,sqlite,sqlite-database,datasette-tool
Author: Michael Bianco
Author-email: mike@mikebian.co
Requires-Python: >=3.10,<4.0
Classifier: License :: OSI Approved :: MIT License
Classifier: Programming Language :: Python :: 3
Classifier: Programming Language :: Python :: 3.10
Classifier: Programming Language :: Python :: 3.11
Classifier: Programming Language :: Python :: 3.12
Requires-Dist: click (>=8.1.7,<9.0.0)
Requires-Dist: ics (>=0.7.2,<0.8.0)
Requires-Dist: sqlite-utils (>=3.36,<4.0)
